gqylpy_datastruct/__init__.py
gqylpy_datastruct/g datastruct.py
gqylpy_datastruct-3.0.dist-info/LICENSE
gqylpy_datastruct-3.0.dist-info/METADATA
gqylpy_datastruct-3.0.dist-info/WHEEL
gqylpy_datastruct-3.0.dist-info/top_level.txt
gqylpy_datastruct-3.0.dist-info/RECORD
