Metadata-Version: 2.1
Name: gqylpy-datastruct
Version: 3.0
Summary: 创建一张蓝图来规划好程序需要的数据结构，并在之后使用该蓝图去校验到来的数据是否如期。
Home-page: http://gqylpy.com
Author: 竹永康
Author-email: <gqylpy@outlook.com>
License: Apache 2.0
Project-URL: Source, https://github.com/gqylpy/gqylpy-datastruct
Classifier: Development Status :: 3 - Alpha
Classifier: Intended Audience :: Developers
Classifier: License :: OSI Approved :: Apache Software License
Classifier: Natural Language :: Chinese (Simplified)
Classifier: Natural Language :: English
Classifier: Operating System :: OS Independent
Classifier: Topic :: Software Development :: Libraries :: Python Modules
Classifier: Topic :: Software Development :: Build Tools
Classifier: Topic :: Software Development :: Object Brokering
Classifier: Topic :: Software Development :: Pre-processors
Classifier: Topic :: Software Development :: Quality Assurance
Classifier: Programming Language :: Python :: 3.8
Classifier: Programming Language :: Python :: 3.9
Classifier: Programming Language :: Python :: 3.10
Classifier: Programming Language :: Python :: 3.11
Classifier: Programming Language :: Python :: 3.12
Requires-Python: >=3.8, <4
License-File: LICENSE
Requires-Dist: gqylpy-exception (>=2.0.4)
